python_fide/__init__.py
python_fide/_enums.py
python_fide/_exceptions.py
python_fide/_parsing.py
python_fide/_typing.py
python_fide/clients/__init__.py
python_fide/clients/_base.py
python_fide/clients/_player_async.py
python_fide/clients/_player_sync.py
python_fide/config/__init__.py
python_fide/config/_base.py
python_fide/config/_player.py
python_fide/types/__init__.py
python_fide/types/_adapters.py
python_fide/types/_annotated.py
python_fide/types/_core.py
python_fide/utils/__init__.py
python_fide/utils/_config.py
python_fide/utils/_general.py
python_fide-0.4.0.dist-info/LICENSE
python_fide-0.4.0.dist-info/METADATA
python_fide-0.4.0.dist-info/WHEEL
python_fide-0.4.0.dist-info/RECORD
