Metadata-Version: 2.3
Name: python-fide
Version: 0.4.0
Summary: Methods to Facilitate Analysis of Fide Ratings
License: MIT
Keywords: chess,fide,ratings,player,news,events
Author: galactixx
Requires-Python: >=3.9
Classifier: License :: OSI Approved :: MIT License
Classifier: Programming Language :: Python :: 3
Classifier: Programming Language :: Python :: 3.9
Classifier: Programming Language :: Python :: 3.10
Classifier: Programming Language :: Python :: 3.11
Classifier: Programming Language :: Python :: 3.12
Classifier: Programming Language :: Python :: 3.13
Requires-Dist: Faker (>=24.11.0)
Requires-Dist: httpx (>=0.27.0)
Requires-Dist: pydantic (>=2.7.0)
Requires-Dist: requests (>=2.31.0)
Requires-Dist: typing_extensions (>=4.6.0)
